ivy/__init__.py
ivy/client_server_example.py
ivy/concept.py
ivy/concept_alpha.py
ivy/concept_interactive_session.py
ivy/concept_space_parsetab.py
ivy/cy_elements.py
ivy/cy_render.py
ivy/cy_styles.py
ivy/dot_layout.py
ivy/general.py
ivy/interrupt_context.py
ivy/iupdr.py
ivy/ivy.py
ivy/ivy2.py
ivy/ivy_actions.py
ivy/ivy_alpha.py
ivy/ivy_art.py
ivy/ivy_ast.py
ivy/ivy_auto_inst.py
ivy/ivy_bmc.py
ivy/ivy_check.py
ivy/ivy_compiler.py
ivy/ivy_concept_space.py
ivy/ivy_congclos.py
ivy/ivy_core.py
ivy/ivy_cpp.py
ivy/ivy_cpp_types.py
ivy/ivy_dafny_ast.py
ivy/ivy_dafny_compiler.py
ivy/ivy_dafny_grammar.py
ivy/ivy_dafny_lexer.py
ivy/ivy_dafny_parser.py
ivy/ivy_dafny_parsetab.py
ivy/ivy_dump.py
ivy/ivy_ev_parser.py
ivy/ivy_ev_viewer.py
ivy/ivy_formulatab.py
ivy/ivy_fragment.py
ivy/ivy_graph.py
ivy/ivy_graph_ui.py
ivy/ivy_graphviz.py
ivy/ivy_init.py
ivy/ivy_interp.py
ivy/ivy_isolate.py
ivy/ivy_l2s.py
ivy/ivy_l2s_old.py
ivy/ivy_launch.py
ivy/ivy_lexer.py
ivy/ivy_libs.py
ivy/ivy_logic.py
ivy/ivy_logic_parser.py
ivy/ivy_logic_parser_gen.py
ivy/ivy_logic_utils.py
ivy/ivy_mc.py
ivy/ivy_module.py
ivy/ivy_parser.py
ivy/ivy_parsetab.py
ivy/ivy_printer.py
ivy/ivy_proof.py
ivy/ivy_resolution.py
ivy/ivy_shell.py
ivy/ivy_show.py
ivy/ivy_smtlib.py
ivy/ivy_solver.py
ivy/ivy_tactics.py
ivy/ivy_temporal.py
ivy/ivy_termtab.py
ivy/ivy_theory.py
ivy/ivy_to_cpp.py
ivy/ivy_to_lean.py
ivy/ivy_to_md.py
ivy/ivy_trace.py
ivy/ivy_transrel.py
ivy/ivy_ui.py
ivy/ivy_ui_cti.py
ivy/ivy_ui_none.py
ivy/ivy_ui_util.py
ivy/ivy_union_find.py
ivy/ivy_unitres.py
ivy/ivy_updr.py
ivy/ivy_utils.py
ivy/ivy_vmt.py
ivy/logic.py
ivy/logic_util.py
ivy/proof.py
ivy/tactics.py
ivy/tactics_api.py
ivy/tk_cy.py
ivy/tk_graph_ui.py
ivy/tk_ui.py
ivy/token_counter.py
ivy/type_inference.py
ivy/ui_extensions_api.py
ivy/widget_analysis_session.py
ivy/widget_cy_graph.py
ivy/widget_dialog.py
ivy/widget_modal.py
ivy/widget_modal_messages.py
ivy/z3_utils.py
ivy/bin/abc
ivy/bin/aigtoaig
ivy/include/picotls.h
ivy/include/z3++.h
ms_ivy-1.8.25.dist-info/METADATA
ms_ivy-1.8.25.dist-info/WHEEL
ms_ivy-1.8.25.dist-info/entry_points.txt
ms_ivy-1.8.25.dist-info/top_level.txt
ms_ivy-1.8.25.dist-info/RECORD
