Metadata-Version: 2.1
Name: ms-ivy
Version: 1.8.25
Summary: IVy verification tool
Home-page: https://github.com/microsoft/ivy
Author: IVy team
Author-email: nomail@example.com
License: MIT
Requires-Dist: pyparsing
Requires-Dist: ply
Requires-Dist: tarjan
Requires-Dist: pydot
Requires-Dist: applescript
